fabricatio_typst-0.1.23.data/scripts/ttm
fabricatio_typst-0.1.23.dist-info/METADATA
fabricatio_typst-0.1.23.dist-info/WHEEL
fabricatio_typst-0.1.23.dist-info/licenses/LICENSE
fabricatio_typst/__init__.py
fabricatio_typst/actions/__init__.py
fabricatio_typst/actions/article.py
fabricatio_typst/actions/article_rag.py
fabricatio_typst/capabilities/__init__.py
fabricatio_typst/capabilities/citation_rag.py
fabricatio_typst/config.py
fabricatio_typst/models/__init__.py
fabricatio_typst/models/aricle_rag.py
fabricatio_typst/models/article_base.py
fabricatio_typst/models/article_essence.py
fabricatio_typst/models/article_main.py
fabricatio_typst/models/article_outline.py
fabricatio_typst/models/article_proposal.py
fabricatio_typst/models/generic.py
fabricatio_typst/models/kwargs_types.py
fabricatio_typst/py.typed
fabricatio_typst/rust.cpython-313-darwin.so
fabricatio_typst/rust.pyi
fabricatio_typst/workflows/__init__.py
fabricatio_typst/workflows/articles.py
fabricatio_typst-0.1.23.dist-info/RECORD
