Metadata-Version: 2.4
Name: fabricatio-typst
Version: 0.1.23
Classifier: License :: OSI Approved :: MIT License
Classifier: Programming Language :: Rust
Classifier: Programming Language :: Python :: 3.12
Classifier: Programming Language :: Python :: 3.13
Classifier: Programming Language :: Python :: 3.14
Classifier: Programming Language :: Python :: Implementation :: CPython
Classifier: Framework :: AsyncIO
Classifier: Framework :: Pydantic :: 2
Classifier: Typing :: Typed
Requires-Dist: fabricatio-core
Requires-Dist: fabricatio-tool
Requires-Dist: fabricatio-capabilities
Requires-Dist: fabricatio-rag
Requires-Dist: fabricatio-typst[workflows,actions] ; extra == 'full'
Requires-Dist: fabricatio-actions ; extra == 'workflows'
Requires-Dist: fabricatio-improve ; extra == 'actions'
Requires-Dist: questionary ; extra == 'actions'
Provides-Extra: full
Provides-Extra: workflows
Provides-Extra: actions
License-File: LICENSE
Summary: A Python library for generating, validating and converting academic content using Typst format.
Author-email: Whth <zettainspector@foxmail.com>
Requires-Python: >=3.12, <3.15
Project-URL: Homepage, https://github.com/Whth/fabricatio
Project-URL: Repository, https://github.com/Whth/fabricatio
Project-URL: Issues, https://github.com/Whth/fabricatio/issues
